{
  "$schema": "mealie-sync",
  "$type": "Foods",
  "$version": "1.0",
  "items": [
    {
      "name": "beschuit",
      "pluralName": "beschuiten",
      "description": "Dubbelgebakken broodproduct; licht en bros, vaak belegd.",
      "aliases": [],
      "label": "Brood & Gebak"
    },
    {
      "name": "bladerdeeg",
      "pluralName": "bladerdeeg",
      "description": "Gelaagd boterdeeg; voor hartige en zoete gebakjes.",
      "aliases": [],
      "label": "Brood & Gebak"
    },
    {
      "name": "brood",
      "pluralName": "broden",
      "description": "Gebakken deegwaar van meel, water en gist; basisvoedsel.",
      "aliases": [],
      "label": "Brood & Gebak"
    },
    {
      "name": "ciabatta",
      "pluralName": "ciabatta's",
      "description": "Italiaans witbrood; luchtig met grote gaten.",
      "aliases": [],
      "label": "Brood & Gebak"
    },
    {
      "name": "croissant",
      "pluralName": "croissants",
      "description": "Frans bladerdeeggebak; boterig en gelaagd.",
      "aliases": [],
      "label": "Brood & Gebak"
    },
    {
      "name": "crouton",
      "pluralName": "croutons",
      "description": "Geroosterd broodblokje; krokante toevoeging in soep of salade.",
      "aliases": [],
      "label": "Brood & Gebak"
    },
    {
      "name": "eierkoek",
      "pluralName": "eierkoeken",
      "description": "Luchtig plat cakeje met eieren; zacht, vaak als tussendoortje.",
      "aliases": [],
      "label": "Brood & Gebak"
    },
    {
      "name": "filodeeg",
      "pluralName": "filodeeg",
      "description": "Zeer dun deegvel; voor baklava en hartige pasteitjes.",
      "aliases": [
        {
          "name": "filobladerdeeg"
        },
        {
          "name": "filo"
        }
      ],
      "label": "Brood & Gebak"
    },
    {
      "name": "hamburgerbroodje",
      "pluralName": "hamburgerbroodjes",
      "description": "Rond zacht broodje; voor burgers.",
      "aliases": [],
      "label": "Brood & Gebak"
    },
    {
      "name": "knäckebröd",
      "pluralName": "knäckebröd",
      "description": "Zweeds knapperbrood; krokant roggebrood.",
      "aliases": [
        {
          "name": "knackebrod"
        },
        {
          "name": "crackers"
        }
      ],
      "label": "Brood & Gebak"
    },
    {
      "name": "libanees brood",
      "pluralName": "libanees brood",
      "description": "Dun platbrood; voor wraps en dips.",
      "aliases": [],
      "label": "Brood & Gebak"
    },
    {
      "name": "loempiavel",
      "pluralName": "loempiavellen",
      "description": "Dunne deegvellen voor loempia's; gevuld en gefrituurd.",
      "aliases": [
        {
          "name": "loempia vel"
        },
        {
          "name": "loempia vellen"
        }
      ],
      "label": "Brood & Gebak"
    },
    {
      "name": "matze",
      "pluralName": "matzes",
      "description": "Ongerezen Joods platbrood; dun en knapperig.",
      "aliases": [
        {
          "name": "matzo"
        },
        {
          "name": "matzot"
        }
      ],
      "label": "Brood & Gebak"
    },
    {
      "name": "naanbrood",
      "pluralName": "naanbrood",
      "description": "Indiaas platbrood; zacht, bij curry.",
      "aliases": [
        {
          "name": "naan"
        }
      ],
      "label": "Brood & Gebak"
    },
    {
      "name": "ontbijtkoek",
      "pluralName": "ontbijtkoeken",
      "description": "Nederlandse kruidkoek; zoet met roggebloem en specerijen.",
      "aliases": [
        {
          "name": "peperkoek"
        }
      ],
      "label": "Brood & Gebak"
    },
    {
      "name": "pitabrood",
      "pluralName": "pitabroodjes",
      "description": "Rond hol Midden-Oosters brood; opent als zakje.",
      "aliases": [
        {
          "name": "pita"
        },
        {
          "name": "pita's"
        }
      ],
      "label": "Brood & Gebak"
    },
    {
      "name": "stokbrood",
      "pluralName": "stokbroden",
      "description": "Frans lang brood; knapperige korst.",
      "aliases": [
        {
          "name": "baguette"
        },
        {
          "name": "baguettes"
        }
      ],
      "label": "Brood & Gebak"
    },
    {
      "name": "maïstortilla",
      "pluralName": "maïstortilla's",
      "description": "Mexicaans platbrood van maïsmeel; glutenvrij, voor taco's en enchiladas.",
      "aliases": [
        {
          "name": "maistortilla"
        },
        {
          "name": "maistortilla's"
        },
        {
          "name": "corn tortilla"
        }
      ],
      "label": "Brood & Gebak"
    },
    {
      "name": "tarwetortilla",
      "pluralName": "tarwetortilla's",
      "description": "Mexicaans platbrood van tarwebloem; zacht en buigzaam, voor wraps en burrito's.",
      "aliases": [
        {
          "name": "flour tortilla"
        }
      ],
      "label": "Brood & Gebak"
    },
    {
      "name": "turks brood",
      "pluralName": "turks brood",
      "description": "Groot plat brood; zacht, voor kebab en wraps.",
      "aliases": [
        {
          "name": "pide"
        }
      ],
      "label": "Brood & Gebak"
    }
  ]
}